.gitlab-ci.yml
.travis.yml
CHANGES.rst
CONTRIBUTORS.rst
DEVELOP.rst
LICENSE.GPL
LICENSE.rst
MANIFEST.in
README.rst
requirements.txt
setup.cfg
setup.py
docs/index.rst
src/collective/__init__.py
src/collective.tiles.rssmixer.egg-info/PKG-INFO
src/collective.tiles.rssmixer.egg-info/SOURCES.txt
src/collective.tiles.rssmixer.egg-info/dependency_links.txt
src/collective.tiles.rssmixer.egg-info/entry_points.txt
src/collective.tiles.rssmixer.egg-info/namespace_packages.txt
src/collective.tiles.rssmixer.egg-info/not-zip-safe
src/collective.tiles.rssmixer.egg-info/requires.txt
src/collective.tiles.rssmixer.egg-info/top_level.txt
src/collective/tiles/__init__.py
src/collective/tiles/rssmixer/__init__.py
src/collective/tiles/rssmixer/configure.zcml
src/collective/tiles/rssmixer/interfaces.py
src/collective/tiles/rssmixer/permissions.zcml
src/collective/tiles/rssmixer/rssmixer.pt
src/collective/tiles/rssmixer/rssmixer.py
src/collective/tiles/rssmixer/setuphandlers.py
src/collective/tiles/rssmixer/testing.py
src/collective/tiles/rssmixer/upgrades.py
src/collective/tiles/rssmixer/upgrades.zcml
src/collective/tiles/rssmixer/locales/README.rst
src/collective/tiles/rssmixer/locales/__init__.py
src/collective/tiles/rssmixer/locales/collective.tiles.rssmixer.pot
src/collective/tiles/rssmixer/locales/manual.pot
src/collective/tiles/rssmixer/locales/update.py
src/collective/tiles/rssmixer/locales/update.sh
src/collective/tiles/rssmixer/locales/en/LC_MESSAGES/collective.tiles.rssmixer.po
src/collective/tiles/rssmixer/locales/it/LC_MESSAGES/collective.tiles.rssmixer.po
src/collective/tiles/rssmixer/profiles/default/browserlayer.xml
src/collective/tiles/rssmixer/profiles/default/catalog.xml
src/collective/tiles/rssmixer/profiles/default/metadata.xml
src/collective/tiles/rssmixer/profiles/default/registry.xml
src/collective/tiles/rssmixer/profiles/default/rolemap.xml
src/collective/tiles/rssmixer/profiles/uninstall/browserlayer.xml
src/collective/tiles/rssmixer/tests/RSS-bar.xml
src/collective/tiles/rssmixer/tests/RSS-foo.xml
src/collective/tiles/rssmixer/tests/__init__.py
src/collective/tiles/rssmixer/tests/test_tile.py